vipen/__init__.py
vipen/cli/__init__.py
vipen/cli/cluster.py
vipen/cli/domain.py
vipen/cli/fix.py
vipen/cli/key.py
vipen/cli/main.py
vipen/cli/monitoring.py
vipen/cli/provider.py
vipen/cli/server.py
vipen/cli/util.py
vipen/core/__init__.py
vipen/core/config.py
vipen/core/logging.py
vipen/core/task.py
vipen/core/utils.py
vipen/monitoring/__init__.py
vipen/monitoring/dashboard_overview.py
vipen/monitoring/dashboard_traffic.py
vipen/monitoring/monitoring.py
vipen/providers/__init__.py
vipen/providers/arvan.py
vipen/providers/base.py
vipen/providers/digitalocean.py
vipen/templates/__init__.py
vipen/templates/base.py
vipen/templates/ss_v2ray_plugin.py
vipen/templates/v2ray_ws_tls_noaead.py
vipen-0.0.2.dist-info/entry_points.txt
vipen-0.0.2.dist-info/WHEEL
vipen-0.0.2.dist-info/METADATA
vipen-0.0.2.dist-info/RECORD
